jaxdiffmodal/__init__.py
jaxdiffmodal/coupling.py
jaxdiffmodal/excitations.py
jaxdiffmodal/features.py
jaxdiffmodal/ftm.py
jaxdiffmodal/losses.py
jaxdiffmodal/lpc.py
jaxdiffmodal/num_utils.py
jaxdiffmodal/time_integrators.py
jaxdiffmodal/utils.py
jaxdiffmodal-0.1.0.dist-info/METADATA
jaxdiffmodal-0.1.0.dist-info/WHEEL
jaxdiffmodal-0.1.0.dist-info/licenses/LICENSE
jaxdiffmodal-0.1.0.dist-info/RECORD
