Metadata-Version: 2.4
Name: jaxdiffmodal
Version: 0.1.0
Summary: A collection of vibration models (e.g. von Kármán plates, tension-modulated and stiff strings) implemented in JAX for fast, differentiable simulations
Project-URL: homepage, https://github.com/rodrigodzf/jaxdiffmodal
Author-email: Rodrigo Diaz <rodrigodzf@gmail.com>
License: GPL-3.0
License-File: LICENSE
Keywords: JAX,acoustics,differentiable,musical instruments,physics,simulation,vibration
Classifier: Development Status :: 3 - Alpha
Classifier: Intended Audience :: Science/Research
Classifier: License :: OSI Approved :: GNU General Public License v3 (GPLv3)
Classifier: Programming Language :: Python :: 3
Classifier: Programming Language :: Python :: 3.11
Classifier: Programming Language :: Python :: 3.12
Classifier: Topic :: Scientific/Engineering :: Physics
Requires-Python: >=3.11
Requires-Dist: einops>=0.8.0
Requires-Dist: equinox>=0.11.12
Requires-Dist: jax>=0.7.0; sys_platform != 'linux'
Requires-Dist: jax[cuda12]>=0.7.0; sys_platform == 'linux'
Requires-Dist: jaxtyping>=0.3.2
Requires-Dist: nemus-magpie
Requires-Dist: numpy==2.1.0
Requires-Dist: scipy>=1.15.1
Requires-Dist: tabulate>=0.9.0
Provides-Extra: benchmark
Requires-Dist: jaxopt>=0.8.3; extra == 'benchmark'
Requires-Dist: librosa>=0.11.0; extra == 'benchmark'
Requires-Dist: lineax>=0.0.7; extra == 'benchmark'
Requires-Dist: llvmlite>=0.44.0; extra == 'benchmark'
Requires-Dist: numba>=0.57; extra == 'benchmark'
Requires-Dist: pandas>=2.2.3; extra == 'benchmark'
Requires-Dist: scienceplots>=2.1.1; extra == 'benchmark'
Requires-Dist: seaborn>=0.13.2; extra == 'benchmark'
Requires-Dist: soxr>=0.5.0.post1; extra == 'benchmark'
Requires-Dist: spectrum>=0.9.0; extra == 'benchmark'
Requires-Dist: torch>=2.4.1; extra == 'benchmark'
Requires-Dist: torchaudio>=2.4.1; extra == 'benchmark'
Provides-Extra: cuda
Requires-Dist: cupy-cuda12x>=13.3.0; extra == 'cuda'
Requires-Dist: cuquantum-python-cu12>=24.11.0; (sys_platform == 'linux') and extra == 'cuda'
Provides-Extra: dev
Requires-Dist: ffmpeg-python>=0.2.0; extra == 'dev'
Requires-Dist: ipykernel>=6.29.5; extra == 'dev'
Requires-Dist: matplotlib>=3.10.0; extra == 'dev'
Requires-Dist: nbclient>=0.10.2; extra == 'dev'
Requires-Dist: nbformat>=5.10.4; extra == 'dev'
Requires-Dist: poethepoet>=0.32.1; extra == 'dev'
Requires-Dist: pytest>=8.4.1; extra == 'dev'
Requires-Dist: quartodoc>=0.11.1; extra == 'dev'
Requires-Dist: ruff>=0.9.2; extra == 'dev'
Requires-Dist: scienceplots>=2.1.1; extra == 'dev'
Requires-Dist: soundfile>=0.13.1; extra == 'dev'
Requires-Dist: tqdm>=4.67.1; extra == 'dev'
